Workbook

Sheet Raw_Data
A1: № | B1: Bank Name | C1: Country | D1: Total Assets (th EUR) | E1: k_in | F1: k_out
A2: 1825 | B2: 1822DIREKT GESELLSCHAFT DER FRANKFURTER SPARKASSE MBH | C2: DE | D2: 10048 | E2: 1 | F2: 0
A3: 2491 | B3: 21 INVEST FRANCE | C3: FR | D3: 0 | E3: 0 | F3: 1
A4: 2088 | B4: 3 BANKEN-GENERALI INVESTMENT-GESELLSCHAFT M.B.H. | C4: AT | D4: 15395 | E4: 0 | F4: 0
A5: 1543 | B5: 321CREDITO - INSTITUICAO FINANCEIRA DE CREDITO, S.A. | C5: PT | D5: 1000350 | E5: 1 | F5: 0
A6: 643 | B6: 365.BANK, A. S. | C6: SK | D6: 4681011 | E6: 1 | F6: 10
A7: 3093 | B7: 3-BANKEN WOHNBAUBANK AG | C7: AT | D7: 103516.51 | E7: 0 | F7: 0
A8: 86 | B8: 3I GROUP PLC | C8: GB | D8: 31174469 | E8: 0 | F8: 89
A9: 1320 | B9: A&G BANCA PRIVADA, S.A. | C9: ES | D9: 596120.17 | E9: 0 | F9: 0
A10: 2021 | B10: A1 BANK AG | C10: AT | D10: 71859 | E10: 0 | F10: 0
A11: 396 | B11: AARGAUISCHE KANTONALBANK | C11: CH | D11: 42185100 | E11: 0 | F11: 5
A12: 2075 | B12: AASEN SPAREBANK | C12: NO | D12: 574238.99 | E12: 2 | F12: 14
A13: 403 | B13: AB SEB BANKAS | C13: LT | D13: 15189148 | E13: 1 | F13: 14
... A3605: 1278 | B3605: ZWECKVERBANDSSPARKASSE RHON-RENNSTEIG | C3605: DE | D3605: 2268701 | E3605: 0 | F3605: 1

Sheet Ownership_Links and calculation
A1: N | B1: Owner | C1: Subs | D1: Direct % | E1: Subsidary Assets (th EUR) | F1: w_ij | G1: Wei | H1: w_ij^2 | I1: Σ_l w_lj^2 | J1: Hij | K1: Delta
A2: 1 | B2: SCHWEIZERISCHE NATIONALBANK | C2: LANDQART AG | D2: 97 | E2: 0 | F2: =IFERROR(D2/100,0) -> 0.97 | G2: =F2*E2 -> 0 | H2: =F2^2 -> 0.9409 | I2: =SUMIF($C:$C,C2,$H:$H) -> 0.9409 | J2: =IF(I2>0,H2/I2,0) -> 1 | K2: =IF((E2+D2)>0,ABS(E2-D2)/(E2+D2),0) -> 1
A3: 2 | B3: SCHWEIZERISCHE NATIONALBANK | C3: ORELL FUESSLI HOLDING AG | D3: 33.3 | E3: 202.13696 | F3: =IFERROR(D3/100,0) -> 0.333 | G3: =F3*E3 -> 67.311609 | H3: =F3^2 -> 0.110889 | I3: =SUMIF($C:$C,C3,$H:$H) -> 0.110889 | J3: =IF(I3>0,H3/I3,0) -> 1 | K3: =IF((E3+D3)>0,ABS(E3-D3)/(E3+D3),0) -> 0.71712174
A4: 3 | B4: SCHWEIZERISCHE NATIONALBANK | C4: BANK FOR INTERNATIONAL SETTLEMENTS, BIS | D4: 3 | E4: 13746443 | F4: =IFERROR(D4/100,0) -> 0.03 | G4: =F4*E4 -> 412393.29 | H4: =F4^2 -> 0.0009 | I4: =SUMIF($C:$C,C4,$H:$H) -> 0.0009 | J4: =IF(I4>0,H4/I4,0) -> 1 | K4: =IF((E4+D4)>0,ABS(E4-D4)/(E4+D4),0) -> 0.99999956
A5: 4 | B5: SCHWEIZERISCHE NATIONALBANK | C5: MOWI ASA | D5: 0.25 | E5: 316507.02 | F5: =IFERROR(D5/100,0) -> 0.0025 | G5: =F5*E5 -> 791.26756 | H5: =F5^2 -> 6.25e-06 | I5: =SUMIF($C:$C,C5,$H:$H) -> 8.472e-05 | J5: =IF(I5>0,H5/I5,0) -> 0.073772427 | K5: =IF((E5+D5)>0,ABS(E5-D5)/(E5+D5),0) -> 0.99999842
A6: 5 | B6: SCHWEIZERISCHE NATIONALBANK | C6: NEL ASA | D6: 0.2 | E6: 18163.45 | F6: =IFERROR(D6/100,0) -> 0.002 | G6: =F6*E6 -> 36.3269 | H6: =F6^2 -> 4e-06 | I6: =SUMIF($C:$C,C6,$H:$H) -> 0.00020407 | J6: =IF(I6>0,H6/I6,0) -> 0.019601117 | K6: =IF((E6+D6)>0,ABS(E6-D6)/(E6+D6),0) -> 0.99997798
A7: 6 | B7: SCHWEIZERISCHE NATIONALBANK | C7: TGS ASA | D7: 0.2 | E7: 116575.28 | F7: =IFERROR(D7/100,0) -> 0.002 | G7: =F7*E7 -> 233.15055 | H7: =F7^2 -> 4e-06 | I7: =SUMIF($C:$C,C7,$H:$H) -> 0.00088526 | J7: =IF(I7>0,H7/I7,0) -> 0.0045184466 | K7: =IF((E7+D7)>0,ABS(E7-D7)/(E7+D7),0) -> 0.99999657
A8: 7 | B8: SCHWEIZERISCHE NATIONALBANK | C8: EUROPRIS ASA | D8: 0.19 | E8: 25451.932 | F8: =IFERROR(D8/100,0) -> 0.0019 | G8: =F8*E8 -> 48.35867 | H8: =F8^2 -> 3.61e-06 | I8: =SUMIF($C:$C,C8,$H:$H) -> 0.00021963 | J8: =IF(I8>0,H8/I8,0) -> 0.016436735 | K8: =IF((E8+D8)>0,ABS(E8-D8)/(E8+D8),0) -> 0.99998507
A9: 8 | B9: SCHWEIZERISCHE NATIONALBANK | C9: NORDIC SEMICONDUCTOR ASA | D9: 0.19 | E9: 24826.27 | F9: =IFERROR(D9/100,0) -> 0.0019 | G9: =F9*E9 -> 47.169912 | H9: =F9^2 -> 3.61e-06 | I9: =SUMIF($C:$C,C9,$H:$H) -> 0.00017142 | J9: =IF(I9>0,H9/I9,0) -> 0.021059386 | K9: =IF((E9+D9)>0,ABS(E9-D9)/(E9+D9),0) -> 0.99998469
A10: 9 | B10: SCHWEIZERISCHE NATIONALBANK | C10: NORSK HYDRO ASA | D10: 0.19 | E10: 597921.14 | F10: =IFERROR(D10/100,0) -> 0.0019 | G10: =F10*E10 -> 1136.0502 | H10: =F10^2 -> 3.61e-06 | I10: =SUMIF($C:$C,C10,$H:$H) -> 3.608e-05 | J10: =IF(I10>0,H10/I10,0) -> 0.10005543 | K10: =IF((E10+D10)>0,ABS(E10-D10)/(E10+D10),0) -> 0.99999936
A11: 10 | B11: SCHWEIZERISCHE NATIONALBANK | C11: ORKLA ASA | D11: 0.19 | E11: 259393.7 | F11: =IFERROR(D11/100,0) -> 0.0019 | G11: =F11*E11 -> 492.84804 | H11: =F11^2 -> 3.61e-06 | I11: =SUMIF($C:$C,C11,$H:$H) -> 4.873e-05 | J11: =IF(I11>0,H11/I11,0) -> 0.074081675 | K11: =IF((E11+D11)>0,ABS(E11-D11)/(E11+D11),0) -> 0.99999854
A12: 11 | B12: SCHWEIZERISCHE NATIONALBANK | C12: SPAREBANK 1 NORD-NORGE | D12: 0.19 | E12: 299141.53 | F12: =IFERROR(D12/100,0) -> 0.0019 | G12: =F12*E12 -> 568.36891 | H12: =F12^2 -> 3.61e-06 | I12: =SUMIF($C:$C,C12,$H:$H) -> 0.00275806 | J12: =IF(I12>0,H12/I12,0) -> 0.001308891 | K12: =IF((E12+D12)>0,ABS(E12-D12)/(E12+D12),0) -> 0.99999873
A13: 12 | B13: SCHWEIZERISCHE NATIONALBANK | C13: STOREBRAND ASA | D13: 0.19 | E13: 2620603.7 | F13: =IFERROR(D13/100,0) -> 0.0019 | G13: =F13*E13 -> 4979.1471 | H13: =F13^2 -> 3.61e-06 | I13: =SUMIF($C:$C,C13,$H:$H) -> 2.733e-05 | J13: =IF(I13>0,H13/I13,0) -> 0.13208928 | K13: =IF((E13+D13)>0,ABS(E13-D13)/(E13+D13),0) -> 0.99999985
... A10001: 10000 | B10001: JP MORGAN SECURITIES PLC | C10001: RYOHIN KEIKAKU CO LTD | D10001: 0.22 | E10001: 6574.0259 | F10001: =IFERROR(D10001/100,0) -> 0.0022 | G10001: =F10001*E10001 -> 14.462857 | H10001: =F10001^2 -> 4.84e-06 | I10001: =SUMIF($C:$C,C10001,$H:$H) -> 4.84e-06 | J10001: =IF(I10001>0,H10001/I10001,0) -> 1 | K10001: =IF((E10001+D10001)>0,ABS(E10001-D10001)/(E10001+D10001),0) -> 0.99993307

Sheet k_in
A1: k_in
A3: Mean | B3: 0.098224195
A4: Standard Error | B4: 0.0069167362
A5: Median | B5: 0
A6: Mode | B6: 0
A7: Standard Deviation | B7: 0.41523466
A8: Sample Variance | B8: 0.17241983
A9: Kurtosis | B9: 76.755999
A10: Skewness | B10: 7.0963412
A11: Range | B11: 8
A12: Minimum | B12: 0
A13: Maximum | B13: 8
A14: Sum | B14: 354
A15: Count | B15: 3604

Sheet k_out
A1: k_out
A3: Mean | B3: 4.3007769
A4: Standard Error | B4: 0.77723114
A5: Median | B5: 0
A6: Mode | B6: 0
A7: Standard Deviation | B7: 46.659769
A8: Sample Variance | B8: 2177.134
A9: Kurtosis | B9: 610.70275
A10: Skewness | B10: 20.636614
A11: Range | B11: 1741
A12: Minimum | B12: 0
A13: Maximum | B13: 1741
A14: Sum | B14: 15500
A15: Count | B15: 3604

Sheet k_in_w
A1: k_in_w
A3: Mean | B3: 3531.022
A4: Standard Error | B4: 614.2272
A5: Median | B5: 0
A6: Mode | B6: 0
A7: Standard Deviation | B7: 61422.72
A8: Sample Variance | B8: 3.7727506e+09
A9: Kurtosis | B9: 727.53473
A10: Skewness | B10: 25.222683
A11: Range | B11: 2207041.2
A12: Minimum | B12: 0
A13: Maximum | B13: 2207041.2
A14: Sum | B14: 35310220
A15: Count | B15: 10000

Sheet S_j
A1: S_j
A3: Mean | B3: 2.0810752
A4: Standard Error | B4: 0.35509871
A5: Median | B5: 0
A6: Mode | B6: 0
A7: Standard Deviation | B7: 21.317756
A8: Sample Variance | B8: 454.44671
A9: Kurtosis | B9: 275.91732
A10: Skewness | B10: 14.971486
A11: Range | B11: 582.21164
A12: Minimum | B12: 0
A13: Maximum | B13: 582.21164
A14: Sum | B14: 7500.1951
A15: Count | B15: 3604

Sheet h_i
A1: h_i
A3: Mean | B3: 1.3005807
A4: Standard Error | B4: 0.25640455
A5: Median | B5: 0
A6: Mode | B6: 0
A7: Standard Deviation | B7: 25.640455
A8: Sample Variance | B8: 657.43293
A9: Kurtosis | B9: 2213.8893
A10: Skewness | B10: 39.882198
A11: Range | B11: 1711.5782
A12: Minimum | B12: 0
A13: Maximum | B13: 1711.5782
A14: Sum | B14: 13005.807
A15: Count | B15: 10000

Sheet Assets mln EUR
A1: Assets mln EUR
A3: Mean | B3: 250233.81
A4: Standard Error | B4: 35532.381
A5: Median | B5: 134.75798
A6: Mode | B6: 0
A7: Standard Deviation | B7: 3553238.1
A8: Sample Variance | B8: 1.2625501e+13
A9: Kurtosis | B9: 1549.5255
A10: Skewness | B10: 36.758095
A11: Range | B11: 1.6952921e+08
A12: Minimum | B12: 0
A13: Maximum | B13: 1.6952921e+08
A14: Sum | B14: 2.5023381e+09
A15: Count | B15: 10000

Sheet K_out calculations
A1: № | B1: Bank Name | G1: Σw_ij (out) | H1: Σw_ij^2 (out) | I1: S_j = (Σw)^2/Σw^2 | J1: h_i
A2: 5 | B2: CAISSE DES DEPOTS ET CONSIGNATIONS | G2: =SUMIF('Ownership_Links and calculation'!$B:$B,$B2,'Ownership_Links and calculation'!$F:$F) -> 311.4721 | H2: =SUMIF('Ownership_Links and calculation'!$B:$B,$B2,'Ownership_Links and calculation'!$H:$H) -> 166.63162 | I2: =IF(H2>0,(G2^2)/H2,0) -> 582.21164 | J2: =SUMIF('Ownership_Links and calculation'!$B:$B,$B2,'Ownership_Links and calculation'!$J:$J) -> 875.95793
A3: 11 | B3: DEUTSCHE BANK AG | G3: =SUMIF('Ownership_Links and calculation'!$B:$B,$B3,'Ownership_Links and calculation'!$F:$F) -> 279.5778 | H3: =SUMIF('Ownership_Links and calculation'!$B:$B,$B3,'Ownership_Links and calculation'!$H:$H) -> 232.59806 | I3: =IF(H3>0,(G3^2)/H3,0) -> 336.04642 | J3: =SUMIF('Ownership_Links and calculation'!$B:$B,$B3,'Ownership_Links and calculation'!$J:$J) -> 460.03766
A4: 13 | B4: CREDIT AGRICOLE SA | G4: =SUMIF('Ownership_Links and calculation'!$B:$B,$B4,'Ownership_Links and calculation'!$F:$F) -> 274.9122 | H4: =SUMIF('Ownership_Links and calculation'!$B:$B,$B4,'Ownership_Links and calculation'!$H:$H) -> 241.13858 | I4: =IF(H4>0,(G4^2)/H4,0) -> 313.41611 | J4: =SUMIF('Ownership_Links and calculation'!$B:$B,$B4,'Ownership_Links and calculation'!$J:$J) -> 355.51492
A5: 3 | B5: BANCO SANTANDER SA | G5: =SUMIF('Ownership_Links and calculation'!$B:$B,$B5,'Ownership_Links and calculation'!$F:$F) -> 232.3255 | H5: =SUMIF('Ownership_Links and calculation'!$B:$B,$B5,'Ownership_Links and calculation'!$H:$H) -> 204.83927 | I5: =IF(H5>0,(G5^2)/H5,0) -> 263.49995 | J5: =SUMIF('Ownership_Links and calculation'!$B:$B,$B5,'Ownership_Links and calculation'!$J:$J) -> 315.65957
A6: 16 | B6: SOCIETE GENERALE | G6: =SUMIF('Ownership_Links and calculation'!$B:$B,$B6,'Ownership_Links and calculation'!$F:$F) -> 213.8038 | H6: =SUMIF('Ownership_Links and calculation'!$B:$B,$B6,'Ownership_Links and calculation'!$H:$H) -> 191.98145 | I6: =IF(H6>0,(G6^2)/H6,0) -> 238.10667 | J6: =SUMIF('Ownership_Links and calculation'!$B:$B,$B6,'Ownership_Links and calculation'!$J:$J) -> 316.89832
A7: 28 | B7: COOPERATIEVE RABOBANK U.A. | G7: =SUMIF('Ownership_Links and calculation'!$B:$B,$B7,'Ownership_Links and calculation'!$F:$F) -> 146.2171 | H7: =SUMIF('Ownership_Links and calculation'!$B:$B,$B7,'Ownership_Links and calculation'!$H:$H) -> 101.49582 | I7: =IF(H7>0,(G7^2)/H7,0) -> 210.64355 | J7: =SUMIF('Ownership_Links and calculation'!$B:$B,$B7,'Ownership_Links and calculation'!$J:$J) -> 247.6663
A8: 41 | B8: BPCE SA | G8: =SUMIF('Ownership_Links and calculation'!$B:$B,$B8,'Ownership_Links and calculation'!$F:$F) -> 196.4844 | H8: =SUMIF('Ownership_Links and calculation'!$B:$B,$B8,'Ownership_Links and calculation'!$H:$H) -> 183.97969 | I8: =IF(H8>0,(G8^2)/H8,0) -> 209.83903 | J8: =SUMIF('Ownership_Links and calculation'!$B:$B,$B8,'Ownership_Links and calculation'!$J:$J) -> 236.64095
A9: 4 | B9: BNP PARIBAS | G9: =SUMIF('Ownership_Links and calculation'!$B:$B,$B9,'Ownership_Links and calculation'!$F:$F) -> 137.0643 | H9: =SUMIF('Ownership_Links and calculation'!$B:$B,$B9,'Ownership_Links and calculation'!$H:$H) -> 119.50208 | I9: =IF(H9>0,(G9^2)/H9,0) -> 157.2075 | J9: =SUMIF('Ownership_Links and calculation'!$B:$B,$B9,'Ownership_Links and calculation'!$J:$J) -> 240.64249
A10: 6 | B10: UBS AG | G10: =SUMIF('Ownership_Links and calculation'!$B:$B,$B10,'Ownership_Links and calculation'!$F:$F) -> 130.6268 | H10: =SUMIF('Ownership_Links and calculation'!$B:$B,$B10,'Ownership_Links and calculation'!$H:$H) -> 110.69266 | I10: =IF(H10>0,(G10^2)/H10,0) -> 154.15078 | J10: =SUMIF('Ownership_Links and calculation'!$B:$B,$B10,'Ownership_Links and calculation'!$J:$J) -> 504.41414
A11: 52 | B11: NORGES BANK | G11: =SUMIF('Ownership_Links and calculation'!$B:$B,$B11,'Ownership_Links and calculation'!$F:$F) -> 72.4157 | H11: =SUMIF('Ownership_Links and calculation'!$B:$B,$B11,'Ownership_Links and calculation'!$H:$H) -> 37.764398 | I11: =IF(H11>0,(G11^2)/H11,0) -> 138.86183 | J11: =SUMIF('Ownership_Links and calculation'!$B:$B,$B11,'Ownership_Links and calculation'!$J:$J) -> 1711.5782
A12: 12 | B12: INTESA SANPAOLO S.P.A. | G12: =SUMIF('Ownership_Links and calculation'!$B:$B,$B12,'Ownership_Links and calculation'!$F:$F) -> 89.4692 | H12: =SUMIF('Ownership_Links and calculation'!$B:$B,$B12,'Ownership_Links and calculation'!$H:$H) -> 67.790728 | I12: =IF(H12>0,(G12^2)/H12,0) -> 118.08013 | J12: =SUMIF('Ownership_Links and calculation'!$B:$B,$B12,'Ownership_Links and calculation'!$J:$J) -> 238.17943
A13: 19 | B13: BARCLAYS BANK PLC | G13: =SUMIF('Ownership_Links and calculation'!$B:$B,$B13,'Ownership_Links and calculation'!$F:$F) -> 87.2056 | H13: =SUMIF('Ownership_Links and calculation'!$B:$B,$B13,'Ownership_Links and calculation'!$H:$H) -> 82.761906 | I13: =IF(H13>0,(G13^2)/H13,0) -> 91.887887 | J13: =SUMIF('Ownership_Links and calculation'!$B:$B,$B13,'Ownership_Links and calculation'!$J:$J) -> 136.30139
... A3563: 3562 | B3563: LAGE LANDEN INTERNATIONAL BV (DE) | G3563: =SUMIF('Ownership_Links and calculation'!$B:$B,$B3563,'Ownership_Links and calculation'!$F:$F) -> 0 | H3563: =SUMIF('Ownership_Links and calculation'!$B:$B,$B3563,'Ownership_Links and calculation'!$H:$H) -> 0 | I3563: =IF(H3563>0,(G3563^2)/H3563,0) -> 0 | J3563: =SUMIF('Ownership_Links and calculation'!$B:$B,$B3563,'Ownership_Links and calculation'!$J:$J) -> 0

Sheet Exponents
C1: Gamma | D1: Delta | E1: Alpha
A2: N | B2: =COUNTA('K_out calculations'!B:B) -> 3563 | C2: =B3/(B2*(B2-1)) -> 0.00028066236 | D2: =AVERAGE('Ownership_Links and calculation'!K:K) -> 0.90309635 | E2: =(1-D2)/(1-C2) -> 0.096930855
A3: L | B3: =COUNTA('K_out calculations'!B:B)-1 -> 3562

Sheet Total descriptive statistic
B3: k_in | C3: k_out | D3: k_in_w | E3: S_j | F3: h_i | G3: Assets mln EUR
A4: Mean | B4: 0.098224195 | C4: 4.3007769 | D4: 3531.022 | E4: 2.0810752 | F4: 1.3005807 | G4: 250233.81
A5: Standard Error | B5: 0.0069167362 | C5: 0.77723114 | D5: 614.2272 | E5: 0.35509871 | F5: 0.25640455 | G5: 35532.381
A6: Standard Deviation | B6: 0.41523466 | C6: 46.659769 | D6: 61422.72 | E6: 21.317756 | F6: 25.640455 | G6: 3553238.1
A7: Sample Variance | B7: 0.17241983 | C7: 2177.134 | D7: 3.7727506e+09 | E7: 454.44671 | F7: 657.43293 | G7: 1.2625501e+13
A8: Kurtosis | B8: 76.755999 | C8: 610.70275 | D8: 727.53473 | E8: 275.91732 | F8: 2213.8893 | G8: 1549.5255
A9: Skewness | B9: 7.0963412 | C9: 20.636614 | D9: 25.222683 | E9: 14.971486 | F9: 39.882198 | G9: 36.758095
A10: Range | B10: 8 | C10: 1741 | D10: 2207041.2 | E10: 582.21164 | F10: 1711.5782 | G10: 1.6952921e+08
A11: Minimum | B11: 0 | C11: 0 | D11: 0 | E11: 0 | F11: 0 | G11: 0
A12: Maximum | B12: 8 | C12: 1741 | D12: 2207041.2 | E12: 582.21164 | F12: 1711.5782 | G12: 1.6952921e+08
A13: Sum | B13: 354 | C13: 15500 | D13: 35310220 | E13: 7500.1951 | F13: 13005.807 | G13: 2.5023381e+09
A14: Count | B14: 3604 | C14: 3604 | D14: 10000 | E14: 3604 | F14: 10000 | G14: 10000

Sheet Descriptive statistic
A1: Descriptive statistic (Direct %)
A3: Mean | B3: 35.31681
A4: Standard Error | B4: 0.40953215
A5: Median | B5: 9.99
A6: Mode | B6: 100
A7: Standard Deviation | B7: 40.953215
A8: Sample Variance | B8: 1677.1659
A9: Kurtosis | B9: -1.2211139
A10: Skewness | B10: 0.71311154
A11: Range | B11: 99.99
A12: Minimum | B12: 0.01
A13: Maximum | B13: 100
A14: Sum | B14: 353168.1
A15: Count | B15: 10000

Sheet Lorenz_Gini_Sj
A1: Metric | B1: Value | D1: Lorenz curve for S_j
A2: N | B2: =COUNTA(_xlfn.UNIQUE('Ownership_Links and calculation'!C:C)) -> 8434
A3: Total | B3: =SUM('K_out calculations'!I:I) -> 4422.6215
A4: Area | B4: =SUM(F10:INDEX(F:F,9+$B$2+8)) -> 0.00016059903
A5: Gini | B5: =1-2*$B$4 -> 0.9996788
A7: rank | B7: value_sorted | C7: cum_value | D7: cum_pop | E7: cum_share | F7: trap_area
A8: 0 | D8: 0 | E8: 0 | F8: 0
A9: 1 | B9: =IF(A9<=$B$2,SMALL('K_out calculations'!$I$2:INDEX('K_out calculations'!$I:$I,$B$2+1),A9+1),NA()) -> 0 | C9: =IF(ISNUMBER(B9),B9,NA()) -> 0 | D9: =IF(A9<=0, 0, (A9-1)/$B$2) -> 0 | E9: =IF(ISNUMBER(C9),C9/$B$3,NA()) -> 0 | F9: 0
A10: 2 | B10: =IF(A10<=$B$2,SMALL('K_out calculations'!$I$2:INDEX('K_out calculations'!$I:$I,$B$2+1),A10+1),NA()) -> 0 | C10: =IF(ISNUMBER(B10),C9+B10,NA()) -> 0 | D10: =IF(A10<=$B$2, (A10-1)/$B$2,NA()) -> 0.0001185677 | E10: =IF(ISNUMBER(C10),C10/$B$3,NA()) -> 0 | F10: =IF(AND(ISNUMBER(E10),ISNUMBER(E9),ISNUMBER(D10),ISNUMBER(D9)),(E10+E9)/2*(D10-D9),NA()) -> 0
A11: 3 | B11: =IF(A11<=$B$2,SMALL('K_out calculations'!$I$2:INDEX('K_out calculations'!$I:$I,$B$2+1),A11+1),NA()) -> 0 | C11: =IF(ISNUMBER(B11),B11,NA()) -> 0 | D11: =IF(A11<=$B$2, (A11-1)/$B$2,NA()) -> 0.0002371354 | E11: =IF(ISNUMBER(C11),C11/$B$3,NA()) -> 0 | F11: =IF(AND(ISNUMBER(E11),ISNUMBER(E10),ISNUMBER(D11),ISNUMBER(D10)),(E11+E10)/2*(D11-D10),NA()) -> 0
A12: 4 | B12: =IF(A12<=$B$2,SMALL('K_out calculations'!$I$2:INDEX('K_out calculations'!$I:$I,$B$2+1),A12+1),NA()) -> 0 | C12: =IF(ISNUMBER(B12),C11+B12,NA()) -> 0 | D12: =IF(A12<=$B$2, (A12-1)/$B$2,NA()) -> 0.00035570311 | E12: =IF(ISNUMBER(C12),C12/$B$3,NA()) -> 0 | F12: =IF(AND(ISNUMBER(E12),ISNUMBER(E11),ISNUMBER(D12),ISNUMBER(D11)),(E12+E11)/2*(D12-D11),NA()) -> 0
A13: 5 | B13: =IF(A13<=$B$2,SMALL('K_out calculations'!$I$2:INDEX('K_out calculations'!$I:$I,$B$2+1),A13+1),NA()) -> 0 | C13: =IF(ISNUMBER(B13),B13,NA()) -> 0 | D13: =IF(A13<=$B$2, (A13-1)/$B$2,NA()) -> 0.00047427081 | E13: =IF(ISNUMBER(C13),C13/$B$3,NA()) -> 0 | F13: =IF(AND(ISNUMBER(E13),ISNUMBER(E12),ISNUMBER(D13),ISNUMBER(D12)),(E13+E12)/2*(D13-D12),NA()) -> 0
A14: 6 | B14: =IF(A14<=$B$2,SMALL('K_out calculations'!$I$2:INDEX('K_out calculations'!$I:$I,$B$2+1),A14+1),NA()) -> 0 | C14: =IF(ISNUMBER(B14),C13+B14,NA()) -> 0 | D14: =IF(A14<=$B$2, (A14-1)/$B$2,NA()) -> 0.00059283851 | E14: =IF(ISNUMBER(C14),C14/$B$3,NA()) -> 0 | F14: =IF(AND(ISNUMBER(E14),ISNUMBER(E13),ISNUMBER(D14),ISNUMBER(D13)),(E14+E13)/2*(D14-D13),NA()) -> 0
A15: 7 | B15: =IF(A15<=$B$2,SMALL('K_out calculations'!$I$2:INDEX('K_out calculations'!$I:$I,$B$2+1),A15+1),NA()) -> 0 | C15: =IF(ISNUMBER(B15),B15,NA()) -> 0 | D15: =IF(A15<=$B$2, (A15-1)/$B$2,NA()) -> 0.00071140621 | E15: =IF(ISNUMBER(C15),C15/$B$3,NA()) -> 0 | F15: =IF(AND(ISNUMBER(E15),ISNUMBER(E14),ISNUMBER(D15),ISNUMBER(D14)),(E15+E14)/2*(D15-D14),NA()) -> 0
A16: 8 | B16: =IF(A16<=$B$2,SMALL('K_out calculations'!$I$2:INDEX('K_out calculations'!$I:$I,$B$2+1),A16+1),NA()) -> 0 | C16: =IF(ISNUMBER(B16),C15+B16,NA()) -> 0 | D16: =IF(A16<=$B$2, (A16-1)/$B$2,NA()) -> 0.00082997392 | E16: =IF(ISNUMBER(C16),C16/$B$3,NA()) -> 0 | F16: =IF(AND(ISNUMBER(E16),ISNUMBER(E15),ISNUMBER(D16),ISNUMBER(D15)),(E16+E15)/2*(D16-D15),NA()) -> 0
A17: 9 | B17: =IF(A17<=$B$2,SMALL('K_out calculations'!$I$2:INDEX('K_out calculations'!$I:$I,$B$2+1),A17+1),NA()) -> 0 | C17: =IF(ISNUMBER(B17),B17,NA()) -> 0 | D17: =IF(A17<=$B$2, (A17-1)/$B$2,NA()) -> 0.00094854162 | E17: =IF(ISNUMBER(C17),C17/$B$3,NA()) -> 0 | F17: =IF(AND(ISNUMBER(E17),ISNUMBER(E16),ISNUMBER(D17),ISNUMBER(D16)),(E17+E16)/2*(D17-D16),NA()) -> 0
A18: 10 | B18: =IF(A18<=$B$2,SMALL('K_out calculations'!$I$2:INDEX('K_out calculations'!$I:$I,$B$2+1),A18+1),NA()) -> 0 | C18: =IF(ISNUMBER(B18),C17+B18,NA()) -> 0 | D18: =IF(A18<=$B$2, (A18-1)/$B$2,NA()) -> 0.0010671093 | E18: =IF(ISNUMBER(C18),C18/$B$3,NA()) -> 0 | F18: =IF(AND(ISNUMBER(E18),ISNUMBER(E17),ISNUMBER(D18),ISNUMBER(D17)),(E18+E17)/2*(D18-D17),NA()) -> 0
A19: 11 | B19: =IF(A19<=$B$2,SMALL('K_out calculations'!$I$2:INDEX('K_out calculations'!$I:$I,$B$2+1),A19+1),NA()) -> 0 | C19: =IF(ISNUMBER(B19),B19,NA()) -> 0 | D19: =IF(A19<=$B$2, (A19-1)/$B$2,NA()) -> 0.001185677 | E19: =IF(ISNUMBER(C19),C19/$B$3,NA()) -> 0 | F19: =IF(AND(ISNUMBER(E19),ISNUMBER(E18),ISNUMBER(D19),ISNUMBER(D18)),(E19+E18)/2*(D19-D18),NA()) -> 0
A20: 12 | B20: =IF(A20<=$B$2,SMALL('K_out calculations'!$I$2:INDEX('K_out calculations'!$I:$I,$B$2+1),A20+1),NA()) -> 0 | C20: =IF(ISNUMBER(B20),C19+B20,NA()) -> 0 | D20: =IF(A20<=$B$2, (A20-1)/$B$2,NA()) -> 0.0013042447 | E20: =IF(ISNUMBER(C20),C20/$B$3,NA()) -> 0 | F20: =IF(AND(ISNUMBER(E20),ISNUMBER(E19),ISNUMBER(D20),ISNUMBER(D19)),(E20+E19)/2*(D20-D19),NA()) -> 0
A21: 13 | B21: =IF(A21<=$B$2,SMALL('K_out calculations'!$I$2:INDEX('K_out calculations'!$I:$I,$B$2+1),A21+1),NA()) -> 0 | C21: =IF(ISNUMBER(B21),B21,NA()) -> 0 | D21: =IF(A21<=$B$2, (A21-1)/$B$2,NA()) -> 0.0014228124 | E21: =IF(ISNUMBER(C21),C21/$B$3,NA()) -> 0 | F21: =IF(AND(ISNUMBER(E21),ISNUMBER(E20),ISNUMBER(D21),ISNUMBER(D20)),(E21+E20)/2*(D21-D20),NA()) -> 0
A22: 14 | B22: =IF(A22<=$B$2,SMALL('K_out calculations'!$I$2:INDEX('K_out calculations'!$I:$I,$B$2+1),A22+1),NA()) -> 0 | C22: =IF(ISNUMBER(B22),C21+B22,NA()) -> 0 | D22: =IF(A22<=$B$2, (A22-1)/$B$2,NA()) -> 0.0015413801 | E22: =IF(ISNUMBER(C22),C22/$B$3,NA()) -> 0 | F22: =IF(AND(ISNUMBER(E22),ISNUMBER(E21),ISNUMBER(D22),ISNUMBER(D21)),(E22+E21)/2*(D22-D21),NA()) -> 0
A23: 15 | B23: =IF(A23<=$B$2,SMALL('K_out calculations'!$I$2:INDEX('K_out calculations'!$I:$I,$B$2+1),A23+1),NA()) -> 0 | C23: =IF(ISNUMBER(B23),B23,NA()) -> 0 | D23: =IF(A23<=$B$2, (A23-1)/$B$2,NA()) -> 0.0016599478 | E23: =IF(ISNUMBER(C23),C23/$B$3,NA()) -> 0 | F23: =IF(AND(ISNUMBER(E23),ISNUMBER(E22),ISNUMBER(D23),ISNUMBER(D22)),(E23+E22)/2*(D23-D22),NA()) -> 0
A24: 16 | B24: =IF(A24<=$B$2,SMALL('K_out calculations'!$I$2:INDEX('K_out calculations'!$I:$I,$B$2+1),A24+1),NA()) -> 0 | C24: =IF(ISNUMBER(B24),C23+B24,NA()) -> 0 | D24: =IF(A24<=$B$2, (A24-1)/$B$2,NA()) -> 0.0017785155 | E24: =IF(ISNUMBER(C24),C24/$B$3,NA()) -> 0 | F24: =IF(AND(ISNUMBER(E24),ISNUMBER(E23),ISNUMBER(D24),ISNUMBER(D23)),(E24+E23)/2*(D24-D23),NA()) -> 0
A25: 17 | B25: =IF(A25<=$B$2,SMALL('K_out calculations'!$I$2:INDEX('K_out calculations'!$I:$I,$B$2+1),A25+1),NA()) -> 0 | C25: =IF(ISNUMBER(B25),B25,NA()) -> 0 | D25: =IF(A25<=$B$2, (A25-1)/$B$2,NA()) -> 0.0018970832 | E25: =IF(ISNUMBER(C25),C25/$B$3,NA()) -> 0 | F25: =IF(AND(ISNUMBER(E25),ISNUMBER(E24),ISNUMBER(D25),ISNUMBER(D24)),(E25+E24)/2*(D25-D24),NA()) -> 0
A26: 18 | B26: =IF(A26<=$B$2,SMALL('K_out calculations'!$I$2:INDEX('K_out calculations'!$I:$I,$B$2+1),A26+1),NA()) -> 0 | C26: =IF(ISNUMBER(B26),C25+B26,NA()) -> 0 | D26: =IF(A26<=$B$2, (A26-1)/$B$2,NA()) -> 0.0020156509 | E26: =IF(ISNUMBER(C26),C26/$B$3,NA()) -> 0 | F26: =IF(AND(ISNUMBER(E26),ISNUMBER(E25),ISNUMBER(D26),ISNUMBER(D25)),(E26+E25)/2*(D26-D25),NA()) -> 0
A27: 19 | B27: =IF(A27<=$B$2,SMALL('K_out calculations'!$I$2:INDEX('K_out calculations'!$I:$I,$B$2+1),A27+1),NA()) -> 0 | C27: =IF(ISNUMBER(B27),B27,NA()) -> 0 | D27: =IF(A27<=$B$2, (A27-1)/$B$2,NA()) -> 0.0021342186 | E27: =IF(ISNUMBER(C27),C27/$B$3,NA()) -> 0 | F27: =IF(AND(ISNUMBER(E27),ISNUMBER(E26),ISNUMBER(D27),ISNUMBER(D26)),(E27+E26)/2*(D27-D26),NA()) -> 0
A28: 20 | B28: =IF(A28<=$B$2,SMALL('K_out calculations'!$I$2:INDEX('K_out calculations'!$I:$I,$B$2+1),A28+1),NA()) -> 0 | C28: =IF(ISNUMBER(B28),C27+B28,NA()) -> 0 | D28: =IF(A28<=$B$2, (A28-1)/$B$2,NA()) -> 0.0022527863 | E28: =IF(ISNUMBER(C28),C28/$B$3,NA()) -> 0 | F28: =IF(AND(ISNUMBER(E28),ISNUMBER(E27),ISNUMBER(D28),ISNUMBER(D27)),(E28+E27)/2*(D28-D27),NA()) -> 0
A29: 21 | B29: =IF(A29<=$B$2,SMALL('K_out calculations'!$I$2:INDEX('K_out calculations'!$I:$I,$B$2+1),A29+1),NA()) -> 0 | C29: =IF(ISNUMBER(B29),B29,NA()) -> 0 | D29: =IF(A29<=$B$2, (A29-1)/$B$2,NA()) -> 0.002371354 | E29: =IF(ISNUMBER(C29),C29/$B$3,NA()) -> 0 | F29: =IF(AND(ISNUMBER(E29),ISNUMBER(E28),ISNUMBER(D29),ISNUMBER(D28)),(E29+E28)/2*(D29-D28),NA()) -> 0
A30: 22 | B30: =IF(A30<=$B$2,SMALL('K_out calculations'!$I$2:INDEX('K_out calculations'!$I:$I,$B$2+1),A30+1),NA()) -> 0 | C30: =IF(ISNUMBER(B30),C29+B30,NA()) -> 0 | D30: =IF(A30<=$B$2, (A30-1)/$B$2,NA()) -> 0.0024899217 | E30: =IF(ISNUMBER(C30),C30/$B$3,NA()) -> 0 | F30: =IF(AND(ISNUMBER(E30),ISNUMBER(E29),ISNUMBER(D30),ISNUMBER(D29)),(E30+E29)/2*(D30-D29),NA()) -> 0
A31: 23 | B31: =IF(A31<=$B$2,SMALL('K_out calculations'!$I$2:INDEX('K_out calculations'!$I:$I,$B$2+1),A31+1),NA()) -> 0 | C31: =IF(ISNUMBER(B31),B31,NA()) -> 0 | D31: =IF(A31<=$B$2, (A31-1)/$B$2,NA()) -> 0.0026084894 | E31: =IF(ISNUMBER(C31),C31/$B$3,NA()) -> 0 | F31: =IF(AND(ISNUMBER(E31),ISNUMBER(E30),ISNUMBER(D31),ISNUMBER(D30)),(E31+E30)/2*(D31-D30),NA()) -> 0
A32: 24 | B32: =IF(A32<=$B$2,SMALL('K_out calculations'!$I$2:INDEX('K_out calculations'!$I:$I,$B$2+1),A32+1),NA()) -> 0 | C32: =IF(ISNUMBER(B32),C31+B32,NA()) -> 0 | D32: =IF(A32<=$B$2, (A32-1)/$B$2,NA()) -> 0.0027270571 | E32: =IF(ISNUMBER(C32),C32/$B$3,NA()) -> 0 | F32: =IF(AND(ISNUMBER(E32),ISNUMBER(E31),ISNUMBER(D32),ISNUMBER(D31)),(E32+E31)/2*(D32-D31),NA()) -> 0
A33: 25 | B33: =IF(A33<=$B$2,SMALL('K_out calculations'!$I$2:INDEX('K_out calculations'!$I:$I,$B$2+1),A33+1),NA()) -> 0 | C33: =IF(ISNUMBER(B33),B33,NA()) -> 0 | D33: =IF(A33<=$B$2, (A33-1)/$B$2,NA()) -> 0.0028456249 | E33: =IF(ISNUMBER(C33),C33/$B$3,NA()) -> 0 | F33: =IF(AND(ISNUMBER(E33),ISNUMBER(E32),ISNUMBER(D33),ISNUMBER(D32)),(E33+E32)/2*(D33-D32),NA()) -> 0
A34: 26 | B34: =IF(A34<=$B$2,SMALL('K_out calculations'!$I$2:INDEX('K_out calculations'!$I:$I,$B$2+1),A34+1),NA()) -> 0 | C34: =IF(ISNUMBER(B34),C33+B34,NA()) -> 0 | D34: =IF(A34<=$B$2, (A34-1)/$B$2,NA()) -> 0.0029641926 | E34: =IF(ISNUMBER(C34),C34/$B$3,NA()) -> 0 | F34: =IF(AND(ISNUMBER(E34),ISNUMBER(E33),ISNUMBER(D34),ISNUMBER(D33)),(E34+E33)/2*(D34-D33),NA()) -> 0
A35: 27 | B35: =IF(A35<=$B$2,SMALL('K_out calculations'!$I$2:INDEX('K_out calculations'!$I:$I,$B$2+1),A35+1),NA()) -> 0 | C35: =IF(ISNUMBER(B35),B35,NA()) -> 0 | D35: =IF(A35<=$B$2, (A35-1)/$B$2,NA()) -> 0.0030827603 | E35: =IF(ISNUMBER(C35),C35/$B$3,NA()) -> 0 | F35: =IF(AND(ISNUMBER(E35),ISNUMBER(E34),ISNUMBER(D35),ISNUMBER(D34)),(E35+E34)/2*(D35-D34),NA()) -> 0
A36: 28 | B36: =IF(A36<=$B$2,SMALL('K_out calculations'!$I$2:INDEX('K_out calculations'!$I:$I,$B$2+1),A36+1),NA()) -> 0 | C36: =IF(ISNUMBER(B36),C35+B36,NA()) -> 0 | D36: =IF(A36<=$B$2, (A36-1)/$B$2,NA()) -> 0.003201328 | E36: =IF(ISNUMBER(C36),C36/$B$3,NA()) -> 0 | F36: =IF(AND(ISNUMBER(E36),ISNUMBER(E35),ISNUMBER(D36),ISNUMBER(D35)),(E36+E35)/2*(D36-D35),NA()) -> 0
A37: 29 | B37: =IF(A37<=$B$2,SMALL('K_out calculations'!$I$2:INDEX('K_out calculations'!$I:$I,$B$2+1),A37+1),NA()) -> 0 | C37: =IF(ISNUMBER(B37),B37,NA()) -> 0 | D37: =IF(A37<=$B$2, (A37-1)/$B$2,NA()) -> 0.0033198957 | E37: =IF(ISNUMBER(C37),C37/$B$3,NA()) -> 0 | F37: =IF(AND(ISNUMBER(E37),ISNUMBER(E36),ISNUMBER(D37),ISNUMBER(D36)),(E37+E36)/2*(D37-D36),NA()) -> 0
A38: 30 | B38: =IF(A38<=$B$2,SMALL('K_out calculations'!$I$2:INDEX('K_out calculations'!$I:$I,$B$2+1),A38+1),NA()) -> 0 | C38: =IF(ISNUMBER(B38),C37+B38,NA()) -> 0 | D38: =IF(A38<=$B$2, (A38-1)/$B$2,NA()) -> 0.0034384634 | E38: =IF(ISNUMBER(C38),C38/$B$3,NA()) -> 0 | F38: =IF(AND(ISNUMBER(E38),ISNUMBER(E37),ISNUMBER(D38),ISNUMBER(D37)),(E38+E37)/2*(D38-D37),NA()) -> 0
A39: 31 | B39: =IF(A39<=$B$2,SMALL('K_out calculations'!$I$2:INDEX('K_out calculations'!$I:$I,$B$2+1),A39+1),NA()) -> 0 | C39: =IF(ISNUMBER(B39),B39,NA()) -> 0 | D39: =IF(A39<=$B$2, (A39-1)/$B$2,NA()) -> 0.0035570311 | E39: =IF(ISNUMBER(C39),C39/$B$3,NA()) -> 0 | F39: =IF(AND(ISNUMBER(E39),ISNUMBER(E38),ISNUMBER(D39),ISNUMBER(D38)),(E39+E38)/2*(D39-D38),NA()) -> 0
A40: 32 | B40: =IF(A40<=$B$2,SMALL('K_out calculations'!$I$2:INDEX('K_out calculations'!$I:$I,$B$2+1),A40+1),NA()) -> 0 | C40: =IF(ISNUMBER(B40),C39+B40,NA()) -> 0 | D40: =IF(A40<=$B$2, (A40-1)/$B$2,NA()) -> 0.0036755988 | E40: =IF(ISNUMBER(C40),C40/$B$3,NA()) -> 0 | F40: =IF(AND(ISNUMBER(E40),ISNUMBER(E39),ISNUMBER(D40),ISNUMBER(D39)),(E40+E39)/2*(D40-D39),NA()) -> 0
A41: 33 | B41: =IF(A41<=$B$2,SMALL('K_out calculations'!$I$2:INDEX('K_out calculations'!$I:$I,$B$2+1),A41+1),NA()) -> 0 | C41: =IF(ISNUMBER(B41),B41,NA()) -> 0 | D41: =IF(A41<=$B$2, (A41-1)/$B$2,NA()) -> 0.0037941665 | E41: =IF(ISNUMBER(C41),C41/$B$3,NA()) -> 0 | F41: =IF(AND(ISNUMBER(E41),ISNUMBER(E40),ISNUMBER(D41),ISNUMBER(D40)),(E41+E40)/2*(D41-D40),NA()) -> 0
A42: 34 | B42: =IF(A42<=$B$2,SMALL('K_out calculations'!$I$2:INDEX('K_out calculations'!$I:$I,$B$2+1),A42+1),NA()) -> 0 | C42: =IF(ISNUMBER(B42),C41+B42,NA()) -> 0 | D42: =IF(A42<=$B$2, (A42-1)/$B$2,NA()) -> 0.0039127342 | E42: =IF(ISNUMBER(C42),C42/$B$3,NA()) -> 0 | F42: =IF(AND(ISNUMBER(E42),ISNUMBER(E41),ISNUMBER(D42),ISNUMBER(D41)),(E42+E41)/2*(D42-D41),NA()) -> 0
A43: 35 | B43: =IF(A43<=$B$2,SMALL('K_out calculations'!$I$2:INDEX('K_out calculations'!$I:$I,$B$2+1),A43+1),NA()) -> 0 | C43: =IF(ISNUMBER(B43),B43,NA()) -> 0 | D43: =IF(A43<=$B$2, (A43-1)/$B$2,NA()) -> 0.0040313019 | E43: =IF(ISNUMBER(C43),C43/$B$3,NA()) -> 0 | F43: =IF(AND(ISNUMBER(E43),ISNUMBER(E42),ISNUMBER(D43),ISNUMBER(D42)),(E43+E42)/2*(D43-D42),NA()) -> 0
A44: 36 | B44: =IF(A44<=$B$2,SMALL('K_out calculations'!$I$2:INDEX('K_out calculations'!$I:$I,$B$2+1),A44+1),NA()) -> 0 | C44: =IF(ISNUMBER(B44),C43+B44,NA()) -> 0 | D44: =IF(A44<=$B$2, (A44-1)/$B$2,NA()) -> 0.0041498696 | E44: =IF(ISNUMBER(C44),C44/$B$3,NA()) -> 0 | F44: =IF(AND(ISNUMBER(E44),ISNUMBER(E43),ISNUMBER(D44),ISNUMBER(D43)),(E44+E43)/2*(D44-D43),NA()) -> 0
A45: 37 | B45: =IF(A45<=$B$2,SMALL('K_out calculations'!$I$2:INDEX('K_out calculations'!$I:$I,$B$2+1),A45+1),NA()) -> 0 | C45: =IF(ISNUMBER(B45),B45,NA()) -> 0 | D45: =IF(A45<=$B$2, (A45-1)/$B$2,NA()) -> 0.0042684373 | E45: =IF(ISNUMBER(C45),C45/$B$3,NA()) -> 0 | F45: =IF(AND(ISNUMBER(E45),ISNUMBER(E44),ISNUMBER(D45),ISNUMBER(D44)),(E45+E44)/2*(D45-D44),NA()) -> 0
A46: 38 | B46: =IF(A46<=$B$2,SMALL('K_out calculations'!$I$2:INDEX('K_out calculations'!$I:$I,$B$2+1),A46+1),NA()) -> 0 | C46: =IF(ISNUMBER(B46),C45+B46,NA()) -> 0 | D46: =IF(A46<=$B$2, (A46-1)/$B$2,NA()) -> 0.004387005 | E46: =IF(ISNUMBER(C46),C46/$B$3,NA()) -> 0 | F46: =IF(AND(ISNUMBER(E46),ISNUMBER(E45),ISNUMBER(D46),ISNUMBER(D45)),(E46+E45)/2*(D46-D45),NA()) -> 0
A47: 39 | B47: =IF(A47<=$B$2,SMALL('K_out calculations'!$I$2:INDEX('K_out calculations'!$I:$I,$B$2+1),A47+1),NA()) -> 0 | C47: =IF(ISNUMBER(B47),B47,NA()) -> 0 | D47: =IF(A47<=$B$2, (A47-1)/$B$2,NA()) -> 0.0045055727 | E47: =IF(ISNUMBER(C47),C47/$B$3,NA()) -> 0 | F47: =IF(AND(ISNUMBER(E47),ISNUMBER(E46),ISNUMBER(D47),ISNUMBER(D46)),(E47+E46)/2*(D47-D46),NA()) -> 0
A48: 40 | B48: =IF(A48<=$B$2,SMALL('K_out calculations'!$I$2:INDEX('K_out calculations'!$I:$I,$B$2+1),A48+1),NA()) -> 0 | C48: =IF(ISNUMBER(B48),C47+B48,NA()) -> 0 | D48: =IF(A48<=$B$2, (A48-1)/$B$2,NA()) -> 0.0046241404 | E48: =IF(ISNUMBER(C48),C48/$B$3,NA()) -> 0 | F48: =IF(AND(ISNUMBER(E48),ISNUMBER(E47),ISNUMBER(D48),ISNUMBER(D47)),(E48+E47)/2*(D48-D47),NA()) -> 0
A49: 41 | B49: =IF(A49<=$B$2,SMALL('K_out calculations'!$I$2:INDEX('K_out calculations'!$I:$I,$B$2+1),A49+1),NA()) -> 0 | C49: =IF(ISNUMBER(B49),B49,NA()) -> 0 | D49: =IF(A49<=$B$2, (A49-1)/$B$2,NA()) -> 0.0047427081 | E49: =IF(ISNUMBER(C49),C49/$B$3,NA()) -> 0 | F49: =IF(AND(ISNUMBER(E49),ISNUMBER(E48),ISNUMBER(D49),ISNUMBER(D48)),(E49+E48)/2*(D49-D48),NA()) -> 0
A50: 42 | B50: =IF(A50<=$B$2,SMALL('K_out calculations'!$I$2:INDEX('K_out calculations'!$I:$I,$B$2+1),A50+1),NA()) -> 0 | C50: =IF(ISNUMBER(B50),C49+B50,NA()) -> 0 | D50: =IF(A50<=$B$2, (A50-1)/$B$2,NA()) -> 0.0048612758 | E50: =IF(ISNUMBER(C50),C50/$B$3,NA()) -> 0 | F50: =IF(AND(ISNUMBER(E50),ISNUMBER(E49),ISNUMBER(D50),ISNUMBER(D49)),(E50+E49)/2*(D50-D49),NA()) -> 0
A51: 43 | B51: =IF(A51<=$B$2,SMALL('K_out calculations'!$I$2:INDEX('K_out calculations'!$I:$I,$B$2+1),A51+1),NA()) -> 0 | C51: =IF(ISNUMBER(B51),B51,NA()) -> 0 | D51: =IF(A51<=$B$2, (A51-1)/$B$2,NA()) -> 0.0049798435 | E51: =IF(ISNUMBER(C51),C51/$B$3,NA()) -> 0 | F51: =IF(AND(ISNUMBER(E51),ISNUMBER(E50),ISNUMBER(D51),ISNUMBER(D50)),(E51+E50)/2*(D51-D50),NA()) -> 0
A52: 44 | B52: =IF(A52<=$B$2,SMALL('K_out calculations'!$I$2:INDEX('K_out calculations'!$I:$I,$B$2+1),A52+1),NA()) -> 0 | C52: =IF(ISNUMBER(B52),C51+B52,NA()) -> 0 | D52: =IF(A52<=$B$2, (A52-1)/$B$2,NA()) -> 0.0050984112 | E52: =IF(ISNUMBER(C52),C52/$B$3,NA()) -> 0 | F52: =IF(AND(ISNUMBER(E52),ISNUMBER(E51),ISNUMBER(D52),ISNUMBER(D51)),(E52+E51)/2*(D52-D51),NA()) -> 0
A53: 45 | B53: =IF(A53<=$B$2,SMALL('K_out calculations'!$I$2:INDEX('K_out calculations'!$I:$I,$B$2+1),A53+1),NA()) -> 0 | C53: =IF(ISNUMBER(B53),B53,NA()) -> 0 | D53: =IF(A53<=$B$2, (A53-1)/$B$2,NA()) -> 0.0052169789 | E53: =IF(ISNUMBER(C53),C53/$B$3,NA()) -> 0 | F53: =IF(AND(ISNUMBER(E53),ISNUMBER(E52),ISNUMBER(D53),ISNUMBER(D52)),(E53+E52)/2*(D53-D52),NA()) -> 0
A54: 46 | B54: =IF(A54<=$B$2,SMALL('K_out calculations'!$I$2:INDEX('K_out calculations'!$I:$I,$B$2+1),A54+1),NA()) -> 0 | C54: =IF(ISNUMBER(B54),C53+B54,NA()) -> 0 | D54: =IF(A54<=$B$2, (A54-1)/$B$2,NA()) -> 0.0053355466 | E54: =IF(ISNUMBER(C54),C54/$B$3,NA()) -> 0 | F54: =IF(AND(ISNUMBER(E54),ISNUMBER(E53),ISNUMBER(D54),ISNUMBER(D53)),(E54+E53)/2*(D54-D53),NA()) -> 0
A55: 47 | B55: =IF(A55<=$B$2,SMALL('K_out calculations'!$I$2:INDEX('K_out calculations'!$I:$I,$B$2+1),A55+1),NA()) -> 0 | C55: =IF(ISNUMBER(B55),B55,NA()) -> 0 | D55: =IF(A55<=$B$2, (A55-1)/$B$2,NA()) -> 0.0054541143 | E55: =IF(ISNUMBER(C55),C55/$B$3,NA()) -> 0 | F55: =IF(AND(ISNUMBER(E55),ISNUMBER(E54),ISNUMBER(D55),ISNUMBER(D54)),(E55+E54)/2*(D55-D54),NA()) -> 0
A56: 48 | B56: =IF(A56<=$B$2,SMALL('K_out calculations'!$I$2:INDEX('K_out calculations'!$I:$I,$B$2+1),A56+1),NA()) -> 0 | C56: =IF(ISNUMBER(B56),C55+B56,NA()) -> 0 | D56: =IF(A56<=$B$2, (A56-1)/$B$2,NA()) -> 0.005572682 | E56: =IF(ISNUMBER(C56),C56/$B$3,NA()) -> 0 | F56: =IF(AND(ISNUMBER(E56),ISNUMBER(E55),ISNUMBER(D56),ISNUMBER(D55)),(E56+E55)/2*(D56-D55),NA()) -> 0
A57: 49 | B57: =IF(A57<=$B$2,SMALL('K_out calculations'!$I$2:INDEX('K_out calculations'!$I:$I,$B$2+1),A57+1),NA()) -> 0 | C57: =IF(ISNUMBER(B57),B57,NA()) -> 0 | D57: =IF(A57<=$B$2, (A57-1)/$B$2,NA()) -> 0.0056912497 | E57: =IF(ISNUMBER(C57),C57/$B$3,NA()) -> 0 | F57: =IF(AND(ISNUMBER(E57),ISNUMBER(E56),ISNUMBER(D57),ISNUMBER(D56)),(E57+E56)/2*(D57-D56),NA()) -> 0
A58: 50 | B58: =IF(A58<=$B$2,SMALL('K_out calculations'!$I$2:INDEX('K_out calculations'!$I:$I,$B$2+1),A58+1),NA()) -> 0 | C58: =IF(ISNUMBER(B58),C57+B58,NA()) -> 0 | D58: =IF(A58<=$B$2, (A58-1)/$B$2,NA()) -> 0.0058098174 | E58: =IF(ISNUMBER(C58),C58/$B$3,NA()) -> 0 | F58: =IF(AND(ISNUMBER(E58),ISNUMBER(E57),ISNUMBER(D58),ISNUMBER(D57)),(E58+E57)/2*(D58-D57),NA()) -> 0
A59: 51 | B59: =IF(A59<=$B$2,SMALL('K_out calculations'!$I$2:INDEX('K_out calculations'!$I:$I,$B$2+1),A59+1),NA()) -> 0 | C59: =IF(ISNUMBER(B59),B59,NA()) -> 0 | D59: =IF(A59<=$B$2, (A59-1)/$B$2,NA()) -> 0.0059283851 | E59: =IF(ISNUMBER(C59),C59/$B$3,NA()) -> 0 | F59: =IF(AND(ISNUMBER(E59),ISNUMBER(E58),ISNUMBER(D59),ISNUMBER(D58)),(E59+E58)/2*(D59-D58),NA()) -> 0
A60: 52 | B60: =IF(A60<=$B$2,SMALL('K_out calculations'!$I$2:INDEX('K_out calculations'!$I:$I,$B$2+1),A60+1),NA()) -> 0 | C60: =IF(ISNUMBER(B60),C59+B60,NA()) -> 0 | D60: =IF(A60<=$B$2, (A60-1)/$B$2,NA()) -> 0.0060469528 | E60: =IF(ISNUMBER(C60),C60/$B$3,NA()) -> 0 | F60: =IF(AND(ISNUMBER(E60),ISNUMBER(E59),ISNUMBER(D60),ISNUMBER(D59)),(E60+E59)/2*(D60-D59),NA()) -> 0
A61: 53 | B61: =IF(A61<=$B$2,SMALL('K_out calculations'!$I$2:INDEX('K_out calculations'!$I:$I,$B$2+1),A61+1),NA()) -> 0 | C61: =IF(ISNUMBER(B61),B61,NA()) -> 0 | D61: =IF(A61<=$B$2, (A61-1)/$B$2,NA()) -> 0.0061655205 | E61: =IF(ISNUMBER(C61),C61/$B$3,NA()) -> 0 | F61: =IF(AND(ISNUMBER(E61),ISNUMBER(E60),ISNUMBER(D61),ISNUMBER(D60)),(E61+E60)/2*(D61-D60),NA()) -> 0
A62: 54 | B62: =IF(A62<=$B$2,SMALL('K_out calculations'!$I$2:INDEX('K_out calculations'!$I:$I,$B$2+1),A62+1),NA()) -> 0 | C62: =IF(ISNUMBER(B62),C61+B62,NA()) -> 0 | D62: =IF(A62<=$B$2, (A62-1)/$B$2,NA()) -> 0.0062840882 | E62: =IF(ISNUMBER(C62),C62/$B$3,NA()) -> 0 | F62: =IF(AND(ISNUMBER(E62),ISNUMBER(E61),ISNUMBER(D62),ISNUMBER(D61)),(E62+E61)/2*(D62-D61),NA()) -> 0
A63: 55 | B63: =IF(A63<=$B$2,SMALL('K_out calculations'!$I$2:INDEX('K_out calculations'!$I:$I,$B$2+1),A63+1),NA()) -> 0 | C63: =IF(ISNUMBER(B63),B63,NA()) -> 0 | D63: =IF(A63<=$B$2, (A63-1)/$B$2,NA()) -> 0.0064026559 | E63: =IF(ISNUMBER(C63),C63/$B$3,NA()) -> 0 | F63: =IF(AND(ISNUMBER(E63),ISNUMBER(E62),ISNUMBER(D63),ISNUMBER(D62)),(E63+E62)/2*(D63-D62),NA()) -> 0
A64: 56 | B64: =IF(A64<=$B$2,SMALL('K_out calculations'!$I$2:INDEX('K_out calculations'!$I:$I,$B$2+1),A64+1),NA()) -> 0 | C64: =IF(ISNUMBER(B64),C63+B64,NA()) -> 0 | D64: =IF(A64<=$B$2, (A64-1)/$B$2,NA()) -> 0.0065212236 | E64: =IF(ISNUMBER(C64),C64/$B$3,NA()) -> 0 | F64: =IF(AND(ISNUMBER(E64),ISNUMBER(E63),ISNUMBER(D64),ISNUMBER(D63)),(E64+E63)/2*(D64-D63),NA()) -> 0
A65: 57 | B65: =IF(A65<=$B$2,SMALL('K_out calculations'!$I$2:INDEX('K_out calculations'!$I:$I,$B$2+1),A65+1),NA()) -> 0 | C65: =IF(ISNUMBER(B65),B65,NA()) -> 0 | D65: =IF(A65<=$B$2, (A65-1)/$B$2,NA()) -> 0.0066397913 | E65: =IF(ISNUMBER(C65),C65/$B$3,NA()) -> 0 | F65: =IF(AND(ISNUMBER(E65),ISNUMBER(E64),ISNUMBER(D65),ISNUMBER(D64)),(E65+E64)/2*(D65-D64),NA()) -> 0
A66: 58 | B66: =IF(A66<=$B$2,SMALL('K_out calculations'!$I$2:INDEX('K_out calculations'!$I:$I,$B$2+1),A66+1),NA()) -> 0 | C66: =IF(ISNUMBER(B66),C65+B66,NA()) -> 0 | D66: =IF(A66<=$B$2, (A66-1)/$B$2,NA()) -> 0.006758359 | E66: =IF(ISNUMBER(C66),C66/$B$3,NA()) -> 0 | F66: =IF(AND(ISNUMBER(E66),ISNUMBER(E65),ISNUMBER(D66),ISNUMBER(D65)),(E66+E65)/2*(D66-D65),NA()) -> 0
A67: 59 | B67: =IF(A67<=$B$2,SMALL('K_out calculations'!$I$2:INDEX('K_out calculations'!$I:$I,$B$2+1),A67+1),NA()) -> 0 | C67: =IF(ISNUMBER(B67),B67,NA()) -> 0 | D67: =IF(A67<=$B$2, (A67-1)/$B$2,NA()) -> 0.0068769267 | E67: =IF(ISNUMBER(C67),C67/$B$3,NA()) -> 0 | F67: =IF(AND(ISNUMBER(E67),ISNUMBER(E66),ISNUMBER(D67),ISNUMBER(D66)),(E67+E66)/2*(D67-D66),NA()) -> 0
A68: 60 | B68: =IF(A68<=$B$2,SMALL('K_out calculations'!$I$2:INDEX('K_out calculations'!$I:$I,$B$2+1),A68+1),NA()) -> 0 | C68: =IF(ISNUMBER(B68),C67+B68,NA()) -> 0 | D68: =IF(A68<=$B$2, (A68-1)/$B$2,NA()) -> 0.0069954944 | E68: =IF(ISNUMBER(C68),C68/$B$3,NA()) -> 0 | F68: =IF(AND(ISNUMBER(E68),ISNUMBER(E67),ISNUMBER(D68),ISNUMBER(D67)),(E68+E67)/2*(D68-D67),NA()) -> 0
A69: 61 | B69: =IF(A69<=$B$2,SMALL('K_out calculations'!$I$2:INDEX('K_out calculations'!$I:$I,$B$2+1),A69+1),NA()) -> 0 | C69: =IF(ISNUMBER(B69),B69,NA()) -> 0 | D69: =IF(A69<=$B$2, (A69-1)/$B$2,NA()) -> 0.0071140621 | E69: =IF(ISNUMBER(C69),C69/$B$3,NA()) -> 0 | F69: =IF(AND(ISNUMBER(E69),ISNUMBER(E68),ISNUMBER(D69),ISNUMBER(D68)),(E69+E68)/2*(D69-D68),NA()) -> 0
A70: 62 | B70: =IF(A70<=$B$2,SMALL('K_out calculations'!$I$2:INDEX('K_out calculations'!$I:$I,$B$2+1),A70+1),NA()) -> 0 | C70: =IF(ISNUMBER(B70),C69+B70,NA()) -> 0 | D70: =IF(A70<=$B$2, (A70-1)/$B$2,NA()) -> 0.0072326298 | E70: =IF(ISNUMBER(C70),C70/$B$3,NA()) -> 0 | F70: =IF(AND(ISNUMBER(E70),ISNUMBER(E69),ISNUMBER(D70),ISNUMBER(D69)),(E70+E69)/2*(D70-D69),NA()) -> 0
A71: 63 | B71: =IF(A71<=$B$2,SMALL('K_out calculations'!$I$2:INDEX('K_out calculations'!$I:$I,$B$2+1),A71+1),NA()) -> 0 | C71: =IF(ISNUMBER(B71),B71,NA()) -> 0 | D71: =IF(A71<=$B$2, (A71-1)/$B$2,NA()) -> 0.0073511975 | E71: =IF(ISNUMBER(C71),C71/$B$3,NA()) -> 0 | F71: =IF(AND(ISNUMBER(E71),ISNUMBER(E70),ISNUMBER(D71),ISNUMBER(D70)),(E71+E70)/2*(D71-D70),NA()) -> 0
A72: 64 | B72: =IF(A72<=$B$2,SMALL('K_out calculations'!$I$2:INDEX('K_out calculations'!$I:$I,$B$2+1),A72+1),NA()) -> 0 | C72: =IF(ISNUMBER(B72),C71+B72,NA()) -> 0 | D72: =IF(A72<=$B$2, (A72-1)/$B$2,NA()) -> 0.0074697652 | E72: =IF(ISNUMBER(C72),C72/$B$3,NA()) -> 0 | F72: =IF(AND(ISNUMBER(E72),ISNUMBER(E71),ISNUMBER(D72),ISNUMBER(D71)),(E72+E71)/2*(D72-D71),NA()) -> 0
A73: 65 | B73: =IF(A73<=$B$2,SMALL('K_out calculations'!$I$2:INDEX('K_out calculations'!$I:$I,$B$2+1),A73+1),NA()) -> 0 | C73: =IF(ISNUMBER(B73),B73,NA()) -> 0 | D73: =IF(A73<=$B$2, (A73-1)/$B$2,NA()) -> 0.0075883329 | E73: =IF(ISNUMBER(C73),C73/$B$3,NA()) -> 0 | F73: =IF(AND(ISNUMBER(E73),ISNUMBER(E72),ISNUMBER(D73),ISNUMBER(D72)),(E73+E72)/2*(D73-D72),NA()) -> 0
A74: 66 | B74: =IF(A74<=$B$2,SMALL('K_out calculations'!$I$2:INDEX('K_out calculations'!$I:$I,$B$2+1),A74+1),NA()) -> 0 | C74: =IF(ISNUMBER(B74),C73+B74,NA()) -> 0 | D74: =IF(A74<=$B$2, (A74-1)/$B$2,NA()) -> 0.0077069006 | E74: =IF(ISNUMBER(C74),C74/$B$3,NA()) -> 0 | F74: =IF(AND(ISNUMBER(E74),ISNUMBER(E73),ISNUMBER(D74),ISNUMBER(D73)),(E74+E73)/2*(D74-D73),NA()) -> 0
A75: 67 | B75: =IF(A75<=$B$2,SMALL('K_out calculations'!$I$2:INDEX('K_out calculations'!$I:$I,$B$2+1),A75+1),NA()) -> 0 | C75: =IF(ISNUMBER(B75),B75,NA()) -> 0 | D75: =IF(A75<=$B$2, (A75-1)/$B$2,NA()) -> 0.0078254683 | E75: =IF(ISNUMBER(C75),C75/$B$3,NA()) -> 0 | F75: =IF(AND(ISNUMBER(E75),ISNUMBER(E74),ISNUMBER(D75),ISNUMBER(D74)),(E75+E74)/2*(D75-D74),NA()) -> 0
A76: 68 | B76: =IF(A76<=$B$2,SMALL('K_out calculations'!$I$2:INDEX('K_out calculations'!$I:$I,$B$2+1),A76+1),NA()) -> 0 | C76: =IF(ISNUMBER(B76),C75+B76,NA()) -> 0 | D76: =IF(A76<=$B$2, (A76-1)/$B$2,NA()) -> 0.007944036 | E76: =IF(ISNUMBER(C76),C76/$B$3,NA()) -> 0 | F76: =IF(AND(ISNUMBER(E76),ISNUMBER(E75),ISNUMBER(D76),ISNUMBER(D75)),(E76+E75)/2*(D76-D75),NA()) -> 0
A77: 69 | B77: =IF(A77<=$B$2,SMALL('K_out calculations'!$I$2:INDEX('K_out calculations'!$I:$I,$B$2+1),A77+1),NA()) -> 0 | C77: =IF(ISNUMBER(B77),B77,NA()) -> 0 | D77: =IF(A77<=$B$2, (A77-1)/$B$2,NA()) -> 0.0080626037 | E77: =IF(ISNUMBER(C77),C77/$B$3,NA()) -> 0 | F77: =IF(AND(ISNUMBER(E77),ISNUMBER(E76),ISNUMBER(D77),ISNUMBER(D76)),(E77+E76)/2*(D77-D76),NA()) -> 0
A78: 70 | B78: =IF(A78<=$B$2,SMALL('K_out calculations'!$I$2:INDEX('K_out calculations'!$I:$I,$B$2+1),A78+1),NA()) -> 0 | C78: =IF(ISNUMBER(B78),C77+B78,NA()) -> 0 | D78: =IF(A78<=$B$2, (A78-1)/$B$2,NA()) -> 0.0081811714 | E78: =IF(ISNUMBER(C78),C78/$B$3,NA()) -> 0 | F78: =IF(AND(ISNUMBER(E78),ISNUMBER(E77),ISNUMBER(D78),ISNUMBER(D77)),(E78+E77)/2*(D78-D77),NA()) -> 0
A79: 71 | B79: =IF(A79<=$B$2,SMALL('K_out calculations'!$I$2:INDEX('K_out calculations'!$I:$I,$B$2+1),A79+1),NA()) -> 0 | C79: =IF(ISNUMBER(B79),B79,NA()) -> 0 | D79: =IF(A79<=$B$2, (A79-1)/$B$2,NA()) -> 0.0082997392 | E79: =IF(ISNUMBER(C79),C79/$B$3,NA()) -> 0 | F79: =IF(AND(ISNUMBER(E79),ISNUMBER(E78),ISNUMBER(D79),ISNUMBER(D78)),(E79+E78)/2*(D79-D78),NA()) -> 0
A80: 72 | B80: =IF(A80<=$B$2,SMALL('K_out calculations'!$I$2:INDEX('K_out calculations'!$I:$I,$B$2+1),A80+1),NA()) -> 0 | C80: =IF(ISNUMBER(B80),C79+B80,NA()) -> 0 | D80: =IF(A80<=$B$2, (A80-1)/$B$2,NA()) -> 0.0084183069 | E80: =IF(ISNUMBER(C80),C80/$B$3,NA()) -> 0 | F80: =IF(AND(ISNUMBER(E80),ISNUMBER(E79),ISNUMBER(D80),ISNUMBER(D79)),(E80+E79)/2*(D80-D79),NA()) -> 0
A81: 73 | B81: =IF(A81<=$B$2,SMALL('K_out calculations'!$I$2:INDEX('K_out calculations'!$I:$I,$B$2+1),A81+1),NA()) -> 0 | C81: =IF(ISNUMBER(B81),B81,NA()) -> 0 | D81: =IF(A81<=$B$2, (A81-1)/$B$2,NA()) -> 0.0085368746 | E81: =IF(ISNUMBER(C81),C81/$B$3,NA()) -> 0 | F81: =IF(AND(ISNUMBER(E81),ISNUMBER(E80),ISNUMBER(D81),ISNUMBER(D80)),(E81+E80)/2*(D81-D80),NA()) -> 0
A82: 74 | B82: =IF(A82<=$B$2,SMALL('K_out calculations'!$I$2:INDEX('K_out calculations'!$I:$I,$B$2+1),A82+1),NA()) -> 0 | C82: =IF(ISNUMBER(B82),C81+B82,NA()) -> 0 | D82: =IF(A82<=$B$2, (A82-1)/$B$2,NA()) -> 0.0086554423 | E82: =IF(ISNUMBER(C82),C82/$B$3,NA()) -> 0 | F82: =IF(AND(ISNUMBER(E82),ISNUMBER(E81),ISNUMBER(D82),ISNUMBER(D81)),(E82+E81)/2*(D82-D81),NA()) -> 0
A83: 75 | B83: =IF(A83<=$B$2,SMALL('K_out calculations'!$I$2:INDEX('K_out calculations'!$I:$I,$B$2+1),A83+1),NA()) -> 0 | C83: =IF(ISNUMBER(B83),B83,NA()) -> 0 | D83: =IF(A83<=$B$2, (A83-1)/$B$2,NA()) -> 0.00877401 | E83: =IF(ISNUMBER(C83),C83/$B$3,NA()) -> 0 | F83: =IF(AND(ISNUMBER(E83),ISNUMBER(E82),ISNUMBER(D83),ISNUMBER(D82)),(E83+E82)/2*(D83-D82),NA()) -> 0
A84: 76 | B84: =IF(A84<=$B$2,SMALL('K_out calculations'!$I$2:INDEX('K_out calculations'!$I:$I,$B$2+1),A84+1),NA()) -> 0 | C84: =IF(ISNUMBER(B84),C83+B84,NA()) -> 0 | D84: =IF(A84<=$B$2, (A84-1)/$B$2,NA()) -> 0.0088925777 | E84: =IF(ISNUMBER(C84),C84/$B$3,NA()) -> 0 | F84: =IF(AND(ISNUMBER(E84),ISNUMBER(E83),ISNUMBER(D84),ISNUMBER(D83)),(E84+E83)/2*(D84-D83),NA()) -> 0
A85: 77 | B85: =IF(A85<=$B$2,SMALL('K_out calculations'!$I$2:INDEX('K_out calculations'!$I:$I,$B$2+1),A85+1),NA()) -> 0 | C85: =IF(ISNUMBER(B85),B85,NA()) -> 0 | D85: =IF(A85<=$B$2, (A85-1)/$B$2,NA()) -> 0.0090111454 | E85: =IF(ISNUMBER(C85),C85/$B$3,NA()) -> 0 | F85: =IF(AND(ISNUMBER(E85),ISNUMBER(E84),ISNUMBER(D85),ISNUMBER(D84)),(E85+E84)/2*(D85-D84),NA()) -> 0
A86: 78 | B86: =IF(A86<=$B$2,SMALL('K_out calculations'!$I$2:INDEX('K_out calculations'!$I:$I,$B$2+1),A86+1),NA()) -> 0 | C86: =IF(ISNUMBER(B86),C85+B86,NA()) -> 0 | D86: =IF(A86<=$B$2, (A86-1)/$B$2,NA()) -> 0.0091297131 | E86: =IF(ISNUMBER(C86),C86/$B$3,NA()) -> 0 | F86: =IF(AND(ISNUMBER(E86),ISNUMBER(E85),ISNUMBER(D86),ISNUMBER(D85)),(E86+E85)/2*(D86-D85),NA()) -> 0
A87: 79 | B87: =IF(A87<=$B$2,SMALL('K_out calculations'!$I$2:INDEX('K_out calculations'!$I:$I,$B$2+1),A87+1),NA()) -> 0 | C87: =IF(ISNUMBER(B87),B87,NA()) -> 0 | D87: =IF(A87<=$B$2, (A87-1)/$B$2,NA()) -> 0.0092482808 | E87: =IF(ISNUMBER(C87),C87/$B$3,NA()) -> 0 | F87: =IF(AND(ISNUMBER(E87),ISNUMBER(E86),ISNUMBER(D87),ISNUMBER(D86)),(E87+E86)/2*(D87-D86),NA()) -> 0
A88: 80 | B88: =IF(A88<=$B$2,SMALL('K_out calculations'!$I$2:INDEX('K_out calculations'!$I:$I,$B$2+1),A88+1),NA()) -> 0 | C88: =IF(ISNUMBER(B88),C87+B88,NA()) -> 0 | D88: =IF(A88<=$B$2, (A88-1)/$B$2,NA()) -> 0.0093668485 | E88: =IF(ISNUMBER(C88),C88/$B$3,NA()) -> 0 | F88: =IF(AND(ISNUMBER(E88),ISNUMBER(E87),ISNUMBER(D88),ISNUMBER(D87)),(E88+E87)/2*(D88-D87),NA()) -> 0
A89: 81 | B89: =IF(A89<=$B$2,SMALL('K_out calculations'!$I$2:INDEX('K_out calculations'!$I:$I,$B$2+1),A89+1),NA()) -> 0 | C89: =IF(ISNUMBER(B89),B89,NA()) -> 0 | D89: =IF(A89<=$B$2, (A89-1)/$B$2,NA()) -> 0.0094854162 | E89: =IF(ISNUMBER(C89),C89/$B$3,NA()) -> 0 | F89: =IF(AND(ISNUMBER(E89),ISNUMBER(E88),ISNUMBER(D89),ISNUMBER(D88)),(E89+E88)/2*(D89-D88),NA()) -> 0
A90: 82 | B90: =IF(A90<=$B$2,SMALL('K_out calculations'!$I$2:INDEX('K_out calculations'!$I:$I,$B$2+1),A90+1),NA()) -> 0 | C90: =IF(ISNUMBER(B90),C89+B90,NA()) -> 0 | D90: =IF(A90<=$B$2, (A90-1)/$B$2,NA()) -> 0.0096039839 | E90: =IF(ISNUMBER(C90),C90/$B$3,NA()) -> 0 | F90: =IF(AND(ISNUMBER(E90),ISNUMBER(E89),ISNUMBER(D90),ISNUMBER(D89)),(E90+E89)/2*(D90-D89),NA()) -> 0
A91: 83 | B91: =IF(A91<=$B$2,SMALL('K_out calculations'!$I$2:INDEX('K_out calculations'!$I:$I,$B$2+1),A91+1),NA()) -> 0 | C91: =IF(ISNUMBER(B91),B91,NA()) -> 0 | D91: =IF(A91<=$B$2, (A91-1)/$B$2,NA()) -> 0.0097225516 | E91: =IF(ISNUMBER(C91),C91/$B$3,NA()) -> 0 | F91: =IF(AND(ISNUMBER(E91),ISNUMBER(E90),ISNUMBER(D91),ISNUMBER(D90)),(E91+E90)/2*(D91-D90),NA()) -> 0
A92: 84 | B92: =IF(A92<=$B$2,SMALL('K_out calculations'!$I$2:INDEX('K_out calculations'!$I:$I,$B$2+1),A92+1),NA()) -> 0 | C92: =IF(ISNUMBER(B92),C91+B92,NA()) -> 0 | D92: =IF(A92<=$B$2, (A92-1)/$B$2,NA()) -> 0.0098411193 | E92: =IF(ISNUMBER(C92),C92/$B$3,NA()) -> 0 | F92: =IF(AND(ISNUMBER(E92),ISNUMBER(E91),ISNUMBER(D92),ISNUMBER(D91)),(E92+E91)/2*(D92-D91),NA()) -> 0
A93: 85 | B93: =IF(A93<=$B$2,SMALL('K_out calculations'!$I$2:INDEX('K_out calculations'!$I:$I,$B$2+1),A93+1),NA()) -> 0 | C93: =IF(ISNUMBER(B93),B93,NA()) -> 0 | D93: =IF(A93<=$B$2, (A93-1)/$B$2,NA()) -> 0.009959687 | E93: =IF(ISNUMBER(C93),C93/$B$3,NA()) -> 0 | F93: =IF(AND(ISNUMBER(E93),ISNUMBER(E92),ISNUMBER(D93),ISNUMBER(D92)),(E93+E92)/2*(D93-D92),NA()) -> 0
A94: 86 | B94: =IF(A94<=$B$2,SMALL('K_out calculations'!$I$2:INDEX('K_out calculations'!$I:$I,$B$2+1),A94+1),NA()) -> 0 | C94: =IF(ISNUMBER(B94),C93+B94,NA()) -> 0 | D94: =IF(A94<=$B$2, (A94-1)/$B$2,NA()) -> 0.010078255 | E94: =IF(ISNUMBER(C94),C94/$B$3,NA()) -> 0 | F94: =IF(AND(ISNUMBER(E94),ISNUMBER(E93),ISNUMBER(D94),ISNUMBER(D93)),(E94+E93)/2*(D94-D93),NA()) -> 0
A95: 87 | B95: =IF(A95<=$B$2,SMALL('K_out calculations'!$I$2:INDEX('K_out calculations'!$I:$I,$B$2+1),A95+1),NA()) -> 0 | C95: =IF(ISNUMBER(B95),B95,NA()) -> 0 | D95: =IF(A95<=$B$2, (A95-1)/$B$2,NA()) -> 0.010196822 | E95: =IF(ISNUMBER(C95),C95/$B$3,NA()) -> 0 | F95: =IF(AND(ISNUMBER(E95),ISNUMBER(E94),ISNUMBER(D95),ISNUMBER(D94)),(E95+E94)/2*(D95-D94),NA()) -> 0
A96: 88 | B96: =IF(A96<=$B$2,SMALL('K_out calculations'!$I$2:INDEX('K_out calculations'!$I:$I,$B$2+1),A96+1),NA()) -> 0 | C96: =IF(ISNUMBER(B96),C95+B96,NA()) -> 0 | D96: =IF(A96<=$B$2, (A96-1)/$B$2,NA()) -> 0.01031539 | E96: =IF(ISNUMBER(C96),C96/$B$3,NA()) -> 0 | F96: =IF(AND(ISNUMBER(E96),ISNUMBER(E95),ISNUMBER(D96),ISNUMBER(D95)),(E96+E95)/2*(D96-D95),NA()) -> 0
A97: 89 | B97: =IF(A97<=$B$2,SMALL('K_out calculations'!$I$2:INDEX('K_out calculations'!$I:$I,$B$2+1),A97+1),NA()) -> 0 | C97: =IF(ISNUMBER(B97),B97,NA()) -> 0 | D97: =IF(A97<=$B$2, (A97-1)/$B$2,NA()) -> 0.010433958 | E97: =IF(ISNUMBER(C97),C97/$B$3,NA()) -> 0 | F97: =IF(AND(ISNUMBER(E97),ISNUMBER(E96),ISNUMBER(D97),ISNUMBER(D96)),(E97+E96)/2*(D97-D96),NA()) -> 0
A98: 90 | B98: =IF(A98<=$B$2,SMALL('K_out calculations'!$I$2:INDEX('K_out calculations'!$I:$I,$B$2+1),A98+1),NA()) -> 0 | C98: =IF(ISNUMBER(B98),C97+B98,NA()) -> 0 | D98: =IF(A98<=$B$2, (A98-1)/$B$2,NA()) -> 0.010552525 | E98: =IF(ISNUMBER(C98),C98/$B$3,NA()) -> 0 | F98: =IF(AND(ISNUMBER(E98),ISNUMBER(E97),ISNUMBER(D98),ISNUMBER(D97)),(E98+E97)/2*(D98-D97),NA()) -> 0
A99: 91 | B99: =IF(A99<=$B$2,SMALL('K_out calculations'!$I$2:INDEX('K_out calculations'!$I:$I,$B$2+1),A99+1),NA()) -> 0 | C99: =IF(ISNUMBER(B99),B99,NA()) -> 0 | D99: =IF(A99<=$B$2, (A99-1)/$B$2,NA()) -> 0.010671093 | E99: =IF(ISNUMBER(C99),C99/$B$3,NA()) -> 0 | F99: =IF(AND(ISNUMBER(E99),ISNUMBER(E98),ISNUMBER(D99),ISNUMBER(D98)),(E99+E98)/2*(D99-D98),NA()) -> 0
A100: 92 | B100: =IF(A100<=$B$2,SMALL('K_out calculations'!$I$2:INDEX('K_out calculations'!$I:$I,$B$2+1),A100+1),NA()) -> 0 | C100: =IF(ISNUMBER(B100),C99+B100,NA()) -> 0 | D100: =IF(A100<=$B$2, (A100-1)/$B$2,NA()) -> 0.010789661 | E100: =IF(ISNUMBER(C100),C100/$B$3,NA()) -> 0 | F100: =IF(AND(ISNUMBER(E100),ISNUMBER(E99),ISNUMBER(D100),ISNUMBER(D99)),(E100+E99)/2*(D100-D99),NA()) -> 0
A101: 93 | B101: =IF(A101<=$B$2,SMALL('K_out calculations'!$I$2:INDEX('K_out calculations'!$I:$I,$B$2+1),A101+1),NA()) -> 0 | C101: =IF(ISNUMBER(B101),B101,NA()) -> 0 | D101: =IF(A101<=$B$2, (A101-1)/$B$2,NA()) -> 0.010908229 | E101: =IF(ISNUMBER(C101),C101/$B$3,NA()) -> 0 | F101: =IF(AND(ISNUMBER(E101),ISNUMBER(E100),ISNUMBER(D101),ISNUMBER(D100)),(E101+E100)/2*(D101-D100),NA()) -> 0
...

Sheet strong banks
A3: Row Labels | B3: Country | C3: Sum of Total Assets (th EUR)
A4: 1822DIREKT GESELLSCHAFT DER FRANKFURTER SPARKASSE MBH | B4: DE | C4: 10048
A5: 21 INVEST FRANCE | B5: FR | C5: 0
A6: 3 BANKEN-GENERALI INVESTMENT-GESELLSCHAFT M.B.H. | B6: AT | C6: 15395
A7: 321CREDITO - INSTITUICAO FINANCEIRA DE CREDITO, S.A. | B7: PT | C7: 1000350
A8: 365.BANK, A. S. | B8: SK | C8: 4681011
A9: 3-BANKEN WOHNBAUBANK AG | B9: AT | C9: 103516.51
A10: 3I GROUP PLC | B10: GB | C10: 31174469
A11: A&G BANCA PRIVADA, S.A. | B11: ES | C11: 596120.17
A12: A1 BANK AG | B12: AT | C12: 71859
A13: AARGAUISCHE KANTONALBANK | B13: CH | C13: 42185100
A14: AASEN SPAREBANK | B14: NO | C14: 574238.99
A15: AB SEB BANKAS | B15: LT | C15: 15189148
... A3602: ZWECKVERBANDSSPARKASSE RHON-RENNSTEIG | B3602: DE | C3602: 2268701
A3603: (blank) | B3603: (blank)
A3604: Grand Total | C3604: 9.6933465e+10

Sheet Sheet10
A3: Row Labels | B3: Sum of Sum of Total Assets (th EUR)
A4: FR | B4: 2.4874719e+10
A5: GB | B5: 2.3091371e+10
A6: DE | B6: 11745137136
A7: ES | B7: 5.6343289e+09
A8: IT | B8: 5545700537
A9: CH | B9: 4.4054761e+09
A10: NL | B10: 4.2611565e+09
A11: NO | B11: 2.5974812e+09
A12: BE | B12: 2578045120
A13: SE | B13: 1.9097167e+09
A14: DK | B14: 1.7569247e+09
A15: IE | B15: 1.3743846e+09
... A34: Grand Total | B34: 9.6933465e+10

Sheet Sheet9
A3: Row Labels | B3: Country | C3: Sum of Total Assets (th EUR)
A4: HSBC HOLDINGS PLC | B4: GB | C4: 2.9040806e+09
A5: BNP PARIBAS | B5: FR | C5: 2704908000
A6: CREDIT AGRICOLE | B6: FR | C6: 2601727000
A7: DEUTSCHE BUNDESBANK | B7: DE | C7: 2372647000
A8: CREDIT AGRICOLE SA | B8: FR | C8: 2309782000
A9: BANCO SANTANDER SA | B9: ES | C9: 1837081000
A10: BARCLAYS PLC | B10: GB | C10: 1.833343e+09
A11: NORGES BANK | B11: NO | C11: 1.757398e+09
A12: GENOSSENSCHAFTLICHER FINANZVERBUND | B12: DE | C12: 1637724000
A13: BPCE GROUP | B13: FR | C13: 1584558000
A14: SOCIETE GENERALE | B14: FR | C14: 1573545000
A15: BANQUE DE FRANCE | B15: FR | C15: 1515709000
... A441: SOCIETE GENERALE INTERNATIONAL LIMITED | B441: GB | C441: 19956772
B442: LT | C442: 19680018
A443: MONETA MONEY BANK, A.S | B443: CZ | C443: 19657895
A444: CAISSE REGIONALE DE CREDIT AGRICOLE MUTUEL DE LA CHAMPAGNE-BOURGOGNE SC | B444: FR | C444: 19611114
A445: ACHMEA BANK NV | B445: NL | C445: 19543852
A446: ROTHSCHILD & CO | B446: FR | C446: 19527113
A447: SACHSEN-FINANZGRUPPE | B447: DE | C447: 19471096
A448: VOLKSWAGEN INTERNATIONAL BELGIUM SA | B448: BE | C448: 19414468
A449: SPAR NORD BANK A/S | B449: DK | C449: 19376060
A450: CAISSE DE REFINANCEMENT DE L'HABITAT SA | B450: FR | C450: 19218927
A451: FRANKFURTER VOLKSBANK RHEIN/MAIN EG | B451: DE | C451: 19214724
A452: BANQUE PALATINE SA | B452: FR | C452: 19187300
A453: UNITED BULGARIAN BANK - UBB | B453: BG | C453: 19154368
A454: CAISSE REGIONALE DE CREDIT AGRICOLE MUTUEL CHARENTE-MARITIME DEUX-SEVRES SC | B454: FR | C454: 19114614
... A602: LANDSHYPOTEK EKONOMISK FORENING | B602: SE | C602: 10849154
B603: BE | C603: 10808936
A604: ATOM HOLDCO LIMITED | B604: GB | C604: 10807093
A605: VOLKSBANK MUNSTERLAND NORD EG | B605: DE | C605: 10786768
A606: ARKEA HOME LOANS SFH | B606: FR | C606: 10763187
A607: ATOM BANK PLC | B607: GB | C607: 10757082
A608: PROCREDIT HOLDING AG | B608: DE | C608: 10751615
A609: EIKA BOLIGKREDITT AS | B609: NO | C609: 10733640
B610: LV | C610: 10646697
A611: SAECHSISCHE AUFBAUBANK FORDERBANK | B611: DE | C611: 10632000
A612: SIEMENS BANK GMBH | B612: DE | C612: 10628393
A613: CAJA RURAL DEL SUR, S. COOP DE CREDITO. | B613: ES | C613: 10617558
A614: RINGKJOBING LANDBOBANK. AKTIESELSKAB | B614: DK | C614: 10596386
A615: CAISSE REGIONALE DE CREDIT AGRICOLE MUTUEL DU CENTRE-OUEST SC | B615: FR | C615: 10563306
A616: BNP PARIBAS LEASE GROUP SA | B616: FR | C616: 10459818
A617: BANK OF MONTREAL EUROPE PLC | B617: IE | C617: 10414441
A618: SOZIALBANK AG | B618: DE | C618: 10400000
A619: SPAREKASSEN DANMARK AF 1871 | B619: DK | C619: 10321263
A620: VOLKSBANK IN OSTWESTFALEN EG | B620: DE | C620: 10282559
A621: RAIFFEISEN-LANDESBANK TIROL AG | B621: AT | C621: 10277445
A622: SR-BOLIGKREDITT AS | B622: NO | C622: 10237079
... A1100: VOLKSBANK RAIFFEISENBANK WUERZBURG EG | B1100: DE | C1100: 2511557
B1101: BE | C1101: 2505252
A1102: BANQUE DEGROOF PETERCAM LUXEMBOURG SA | B1102: LU | C1102: 2496750
A1103: SPAREBANK 1 OSTFOLD AKERSHUS | B1103: NO | C1103: 2495100.2
A1104: EUROPE ARAB BANK PLC | B1104: GB | C1104: 2490273
A1105: KREISSPARKASSE GRAFSCHAFT BENTHEIM ZU NORDHORN | B1105: DE | C1105: 2490039
A1106: BANCO FINANTIA SA | B1106: PT | C1106: 2482606
A1107: RENTA 4 BANCO, S.A. | B1107: ES | C1107: 2479893
A1108: CAJA RURAL DE SORIA SOCIEDAD COOPERATIVA DE CREDITO | B1108: ES | C1108: 2474124
A1109: MMB SCF | B1109: FR | C1109: 2473682
A1110: KREISSPARKASSE HEIDENHEIM | B1110: DE | C1110: 2472869
A1111: BANCA CENTROPADANA - CREDITO COOPERATIVO SCRL | B1111: IT | C1111: 2467945
A1112: SABADELL CONSUMER FINANCE, S.A. | B1112: ES | C1112: 2454394.1
B1113: BE | C1113: 2452868
A1114: KREISSPARKASSE MAERKISCH-ODERLAND | B1114: DE | C1114: 2445832
A1115: KREIS- UND STADTSPARKASSE ERDING-DORFEN | B1115: DE | C1115: 2438425
A1116: CARIFERMO - CASSA DI RISPARMIO DI FERMO SPA | B1116: IT | C1116: 2422462
A1117: CAMBRIDGE BUILDING SOCIETY | B1117: GB | C1117: 2422064.9
A1118: SPAREBANK 1 NORDMORE | B1118: NO | C1118: 2419113.4
A1119: BLU BANCA S.P.A. | B1119: IT | C1119: 2418178
A1120: VR-BANK PASSAU EG | B1120: DE | C1120: 2410181
A1121: JULIAN HODGE BANK LIMITED | B1121: GB | C1121: 2405409.7
A1122: SPARKASSE NEU-ULM-ILLERTISSEN | B1122: DE | C1122: 2398947
A1123: TRIODOS BANK UK LIMITED | B1123: GB | C1123: 2372074.9
A1124: DELAVSKA HRANILNICA DD LJUBLJANA | B1124: SI | C1124: 2367174
A1125: BUSTADKREDITT SOGN OG FJORDANE AS | B1125: NO | C1125: 2365918.6
... A1314: SINGULAR BANK S.A.U | B1314: ES | C1314: 1604558
B1315: ES | C1315: 1602686.9
A1316: JAEREN SPAREBANK | B1316: NO | C1316: 1598831.7
A1317: CSOB LEASING, A.S. | B1317: SK | C1317: 1598352
A1318: BULGARIAN DEVELOPMENT BANK AD | B1318: BG | C1318: 1583176.6
A1319: KREISSPARKASSE SAALFELD-RUDOLSTADT | B1319: DE | C1319: 1582707
A1320: CIF EUROMORTGAGE | B1320: FR | C1320: 1582334
A1321: AMERICAN EXPRESS CARTE FRANCE SA | B1321: FR | C1321: 1580557
A1322: DEZELNA BANKA SLOVENIJE DD. | B1322: SI | C1322: 1580214
A1323: MEDIOCREDITO TRENTINO-ALTO ADIGE SPA | B1323: IT | C1323: 1579665
A1324: INTERNATIONAL CARD SERVICES BV | B1324: NL | C1324: 1576814
A1325: SPARKASSE UNSTRUT-HAINICH | B1325: DE | C1325: 1575131
A1326: BCC DI VENEZIA, PADOVA E ROVIGO - BANCA ANNIA | B1326: IT | C1326: 1574100
A1327: VIVIBANCA | B1327: IT | C1327: 1562046
... A1707: HOELAND OG SETSKOG SPAREBANK | B1707: NO | C1707: 730184.92
B1708: BG | C1708: 729645.36
A1709: DALSLANDS SPARBANK | B1709: SE | C1709: 726964.33
A1710: SPARKASSE BONNDORF-STUEHLINGEN | B1710: DE | C1710: 725601
A1711: PACIFIC HORIZON INVESTMENT TRUST PLC | B1711: GB | C1711: 724816.56
A1712: EIDSBERG SPAREBANK | B1712: NO | C1712: 724549.43
A1713: CAIXA DE CREDITO AGRICOLA MUTUO DE POVOA DE VARZIM, VILA DO CONDE E ESPOSENDE CRL | B1713: PT | C1713: 723864
A1714: ZKB ZADRUZNA KRASKA BANKA TRST GORICA ZADRUGA - ZKB CREDITO COOPERATIVO DI TRIESTE E GORIZIA SOCIETA COOPERATIVA | B1714: IT | C1714: 723187
A1715: PODRAVSKA BANKA D.D. | B1715: HR | C1715: 723071
A1716: MERKUR ANDELSKASSE | B1716: DK | C1716: 722511.37
A1717: BANCA DI CREDITO COOPERATIVO DI RECANATI E COLMURANO (COMUNE DI RECANATI - PROVINCIA DI MACERATA) | B1717: IT | C1717: 720994
A1718: BANCA CREDIFARMA S.P.A. | B1718: IT | C1718: 719482
...
